MANIFEST.in
README.rst
os_networksv2_python_novaclient_ext.py
setup.py
os_networksv2_python_novaclient_ext.egg-info/PKG-INFO
os_networksv2_python_novaclient_ext.egg-info/SOURCES.txt
os_networksv2_python_novaclient_ext.egg-info/dependency_links.txt
os_networksv2_python_novaclient_ext.egg-info/pbr.json
os_networksv2_python_novaclient_ext.egg-info/requires.txt
os_networksv2_python_novaclient_ext.egg-info/top_level.txt