Metadata-Version: 1.1
Name: os-networksv2-python-novaclient-ext
Version: 0.23
Summary: Adds rackspace networks support to python-novaclient
Home-page: https://github.com/rackerlabs/os_networksv2_python_novaclient_ext
Author: Rackspace
Author-email: jkoelker@rackspace.com, matt.dietz@rackspace.com
License: Apache License, Version 2.0
Platform: UNKNOWN
Classifier: Development Status :: 3 - Alpha
Classifier: Intended Audience :: Developers
Classifier: Intended Audience :: Information Technology
Classifier: License :: OSI Approved :: Apache Software License
Classifier: Operating System :: OS Independent
Classifier: Programming Language :: Python
